mygoogleAuth/__init__.py
mygoogleAuth/mygoogleAuth.py
mygoogleAuth-0.2.0.dist-info/METADATA
mygoogleAuth-0.2.0.dist-info/WHEEL
mygoogleAuth-0.2.0.dist-info/top_level.txt
mygoogleAuth-0.2.0.dist-info/RECORD
