Metadata-Version: 2.1
Name: mygoogleAuth
Version: 0.2.0
Summary: google認証用の便利クラス
Home-page: https://github.com/lupin-oomura/mygoogleAuth.git
Author: Shin Oomura
Author-email: shin.oomura@gmail.com
Requires-Dist: flask
Requires-Dist: flask-login
Requires-Dist: oauthlib
Requires-Dist: requests
Requires-Dist: cryptography
